LICENSE
MANIFEST.in
README.rst
setup.py
nubo/__init__.py
nubo/config.py
nubo/remote.py
nubo.egg-info/PKG-INFO
nubo.egg-info/SOURCES.txt
nubo.egg-info/dependency_links.txt
nubo.egg-info/requires.txt
nubo.egg-info/top_level.txt
nubo/clouds/__init__.py
nubo/clouds/base.py
nubo/clouds/digitalocean.py
nubo/clouds/ec2.py
nubo/clouds/linode.py
nubo/clouds/opennebula.py
nubo/clouds/rackspace.py
scripts/nubo