Metadata-Version: 1.1
Name: nubo
Version: 0.7
Summary: Virtual Machine deployments on multiple cloud providers
Home-page: http://pythonhosted.org/nubo
Author: Emanuele Rocca
Author-email: ema@linux.it
License: BSD
Keywords: cloud vm startup devops ec2 rackspace linode
Platform: UNKNOWN
Classifier: Development Status :: 4 - Beta
Classifier: Environment :: Console
Classifier: License :: OSI Approved :: BSD License
Classifier: Programming Language :: Python
Classifier: Intended Audience :: Developers
Classifier: Intended Audience :: System Administrators
Classifier: Topic :: Internet
Classifier: Topic :: System
